cmakelint/__init__.py
cmakelint/__main__.py
cmakelint/__version__.py
cmakelint/cli.py
cmakelint/error_code.py
cmakelint/lint.py
cmakelint/rules.py
cmakelint/state.py
cmake_lint_paddle-1.5.2.dist-info/LICENSE
cmake_lint_paddle-1.5.2.dist-info/METADATA
cmake_lint_paddle-1.5.2.dist-info/WHEEL
cmake_lint_paddle-1.5.2.dist-info/entry_points.txt
cmake_lint_paddle-1.5.2.dist-info/top_level.txt
cmake_lint_paddle-1.5.2.dist-info/RECORD
