Metadata-Version: 2.1
Name: cmake-lint-paddle
Version: 1.5.2
Summary: A fork of cmake-lint for PaddlePaddle
Author-email: Richard Quirk <richard.quirk@gmail.com>, Nyakku Shigure <sigure.qaq@gmail.com>
License: Apache 2.0
Project-URL: Homepage, https://github.com/PFCCLab/cmake-lint-paddle
Project-URL: Documentation, https://github.com/PFCCLab/cmake-lint-paddle
Keywords: cmake,lint
Classifier: Environment :: Console
Classifier: Operating System :: OS Independent
Classifier: License :: OSI Approved :: Apache Software License
Classifier: Programming Language :: Python
Classifier: Programming Language :: Python :: 3
Classifier: Programming Language :: Python :: 3.8
Classifier: Programming Language :: Python :: 3.9
Classifier: Programming Language :: Python :: 3.10
Classifier: Programming Language :: Python :: 3.11
Classifier: Programming Language :: Python :: 3.12
Classifier: Programming Language :: Python :: 3.13
Classifier: Programming Language :: Python :: Implementation :: CPython
Requires-Python: >=3.8
License-File: LICENSE
